nwbmatic/__init__.py
nwbmatic/allends.py
nwbmatic/cnmfe.py
nwbmatic/ephys_gui.py
nwbmatic/loader.py
nwbmatic/loader_gui.py
nwbmatic/misc.py
nwbmatic/neurosuite.py
nwbmatic/ophys_gui.py
nwbmatic/phy.py
nwbmatic/suite2p.py
nwbmatic-0.1.2.dist-info/LICENSE
nwbmatic-0.1.2.dist-info/METADATA
nwbmatic-0.1.2.dist-info/WHEEL
nwbmatic-0.1.2.dist-info/top_level.txt
nwbmatic-0.1.2.dist-info/RECORD
