Metadata-Version: 2.1
Name: nwbmatic
Version: 0.1.2
Summary: NWB creator from various data streams
Author-email: Guillaume Viejo <guillaume.viejo@gmail.com>
License: GNU GENERAL PUBLIC LICENSE
Project-URL: homepage, https://github.com/pynapple-org/nwbmatic
Project-URL: documentation, https://pynapple-org.github.io/nwbmatic/
Project-URL: repository, https://github.com/pynapple-org/nwbmatic
Keywords: neuroscience
Classifier: Development Status :: 3 - Alpha
Classifier: Intended Audience :: Science/Research
Classifier: License :: OSI Approved :: GNU General Public License v3 (GPLv3)
Classifier: Natural Language :: English
Classifier: Programming Language :: Python :: 3
Requires-Python: >=3.8
License-File: LICENSE
Requires-Dist: pandas >=1.0.3
Requires-Dist: numpy >=1.17.4
Requires-Dist: scipy >=1.3.2
Requires-Dist: numba >=0.46.0
Requires-Dist: pynapple
Requires-Dist: pynwb
Requires-Dist: tabulate
Requires-Dist: h5py
Requires-Dist: tifffile
Requires-Dist: zarr
Provides-Extra: allen
Requires-Dist: allensdk >=2.15.1 ; extra == 'allen'
Provides-Extra: dev
Requires-Dist: black ; extra == 'dev'
Requires-Dist: isort ; extra == 'dev'
Requires-Dist: pip-tools ; extra == 'dev'
Requires-Dist: pytest ; extra == 'dev'
Requires-Dist: flake8 ; extra == 'dev'
Requires-Dist: coverage ; extra == 'dev'
